Metadata-Version: 2.4
Name: shadowseal
Version: 2.0.0
Summary: Secure Python encryption and execution framework with cross-platform support
Home-page: https://github.com/AFTeam-Owner/shadowseal
Author: Monarch of Shadows
Author-email: Monarch of Shadows <farhanbd637@gmail.com>
License: MIT
Project-URL: Homepage, https://github.com/AFTeam-Owner/shadowseal
Project-URL: Repository, https://github.com/AFTeam-Owner/shadowseal
Project-URL: Issues, https://github.com/AFTeam-Owner/shadowseal/issues
Keywords: encryption,obfuscation,security,python,anti-debugging,android,termux
Classifier: Development Status :: 5 - Production/Stable
Classifier: Intended Audience :: Developers
Classifier: License :: OSI Approved :: MIT License
Classifier: Operating System :: OS Independent
Classifier: Operating System :: POSIX :: Linux
Classifier: Operating System :: Microsoft :: Windows
Classifier: Operating System :: MacOS
Classifier: Programming Language :: Python :: 3
Classifier: Programming Language :: Python :: 3.7
Classifier: Programming Language :: Python :: 3.8
Classifier: Programming Language :: Python :: 3.9
Classifier: Programming Language :: Python :: 3.10
Classifier: Programming Language :: Python :: 3.11
Classifier: Programming Language :: Python :: 3.12
Classifier: Topic :: Security :: Cryptography
Classifier: Topic :: Software Development :: Build Tools
Classifier: Topic :: System :: Systems Administration
Requires-Python: >=3.7
License-File: LICENSE
Requires-Dist: cython>=3.0
Requires-Dist: cryptography>=41.0.0
Requires-Dist: psutil>=5.8.0
Provides-Extra: dev
Requires-Dist: pytest>=6.0; extra == "dev"
Requires-Dist: pytest-cov>=2.0; extra == "dev"
Requires-Dist: black>=21.0; extra == "dev"
Requires-Dist: flake8>=3.8; extra == "dev"
Requires-Dist: mypy>=0.800; extra == "dev"
Provides-Extra: android
Requires-Dist: psutil>=5.8.0; extra == "android"
Dynamic: author
Dynamic: home-page
Dynamic: license-file
Dynamic: requires-python
